betapert/__init__.py
betapert/funcs.py
betapert-0.1.5.dist-info/METADATA
betapert-0.1.5.dist-info/WHEEL
betapert-0.1.5.dist-info/RECORD
