Metadata-Version: 2.1
Name: betapert
Version: 0.1.5
Summary: Top-level package for beta-PERT distribution.
Home-page: https://github.com/tadamcz/betapert
Author: Tom Adamczewski
Author-email: tadamczewskipublic@gmail.com
Requires-Python: >=3.9,<3.13
Classifier: Natural Language :: English
Classifier: Programming Language :: Python :: 3
Classifier: Programming Language :: Python :: 3.9
Classifier: Programming Language :: Python :: 3.10
Classifier: Programming Language :: Python :: 3.11
Requires-Dist: scipy (>=1.10.1,<2.0.0)
